json_category_counter/__init__.py
json_category_counter/counter.py
json_category_counter-0.1.0.dist-info/METADATA
json_category_counter-0.1.0.dist-info/WHEEL
json_category_counter-0.1.0.dist-info/top_level.txt
json_category_counter-0.1.0.dist-info/RECORD
