Metadata-Version: 2.1
Name: json-category-counter
Version: 0.1.0
Summary: A package to count categories and tests from a JSON file
Author: Zheng,yang
Author-email: your-email@example.com
Classifier: Programming Language :: Python :: 3
Classifier: License :: OSI Approved :: MIT License
Classifier: Operating System :: OS Independent
Requires-Python: >=3.6
